[
    {
      "name": "Estados Unidos",
      "code": "US",
      "states": [
        { "name": "Alabama", "code": "AL", "number": 1 },
        { "name": "Alaska", "code": "AK", "number": 2 },
        { "name": "Arizona", "code": "AZ", "number": 3 },
        { "name": "Arkansas", "code": "AR", "number": 4 },
        { "name": "California", "code": "CA", "number": 5 },
        { "name": "Colorado", "code": "CO", "number": 6 },
        { "name": "Connecticut", "code": "CT", "number": 7 },
        { "name": "Delaware", "code": "DE", "number": 8 },
        { "name": "Florida", "code": "FL", "number": 9 },
        { "name": "Georgia", "code": "GA", "number": 10 },
        { "name": "Hawái", "code": "HI", "number": 11 },
        { "name": "Idaho", "code": "ID", "number": 12 },
        { "name": "Illinois", "code": "IL", "number": 13 },
        { "name": "Indiana", "code": "IN", "number": 14 },
        { "name": "Iowa", "code": "IA", "number": 15 },
        { "name": "Kansas", "code": "KS", "number": 16 },
        { "name": "Kentucky", "code": "KY", "number": 17 },
        { "name": "Luisiana", "code": "LA", "number": 18 },
        { "name": "Maine", "code": "ME", "number": 19 },
        { "name": "Maryland", "code": "MD", "number": 20 },
        { "name": "Massachusetts", "code": "MA", "number": 21 },
        { "name": "Míchigan", "code": "MI", "number": 22 },
        { "name": "Minnesota", "code": "MN", "number": 23 },
        { "name": "Misisipi", "code": "MS", "number": 24 },
        { "name": "Misuri", "code": "MO", "number": 25 },
        { "name": "Montana", "code": "MT", "number": 26 },
        { "name": "Nebraska", "code": "NE", "number": 27 },
        { "name": "Nevada", "code": "NV", "number": 28 },
        { "name": "Nuevo Hampshire", "code": "NH", "number": 29 },
        { "name": "Nueva Jersey", "code": "NJ", "number": 30 },
        { "name": "Nuevo México", "code": "NM", "number": 31 },
        { "name": "Nueva York", "code": "NY", "number": 32 },
        { "name": "Carolina del Norte", "code": "NC", "number": 33 },
        { "name": "Dakota del Norte", "code": "ND", "number": 34 },
        { "name": "Ohio", "code": "OH", "number": 35 },
        { "name": "Oklahoma", "code": "OK", "number": 36 },
        { "name": "Oregón", "code": "OR", "number": 37 },
        { "name": "Pensilvania", "code": "PA", "number": 38 },
        { "name": "Rhode Island", "code": "RI", "number": 39 },
        { "name": "Carolina del Sur", "code": "SC", "number": 40 },
        { "name": "Dakota del Sur", "code": "SD", "number": 41 },
        { "name": "Tennessee", "code": "TN", "number": 42 },
        { "name": "Texas", "code": "TX", "number": 43 },
        { "name": "Utah", "code": "UT", "number": 44 },
        { "name": "Vermont", "code": "VT", "number": 45 },
        { "name": "Virginia", "code": "VA", "number": 46 },
        { "name": "Washington", "code": "WA", "number": 47 },
        { "name": "Virginia Occidental", "code": "WV", "number": 48 },
        { "name": "Wisconsin", "code": "WI", "number": 49 },
        { "name": "Wyoming", "code": "WY", "number": 50 }
      ]
    },
    {
      "name": "México",
      "code": "MX",
      "states": [
        { "name": "Aguascalientes", "code": "AGU", "number": 1 },
        { "name": "Baja California", "code": "BC", "number": 2 },
        { "name": "Baja California Sur", "code": "BCS", "number": 3 },
        { "name": "Campeche", "code": "CAM", "number": 4 },
        { "name": "Chiapas", "code": "CHIS", "number": 5 },
        { "name": "Chihuahua", "code": "CHIH", "number": 6 },
        { "name": "Ciudad de México", "code": "CDMX", "number": 7 },
        { "name": "Coahuila", "code": "COAH", "number": 8 },
        { "name": "Colima", "code": "COL", "number": 9 },
        { "name": "Durango", "code": "DGO", "number": 10 },
        { "name": "Guanajuato", "code": "GTO", "number": 11 },
        { "name": "Guerrero", "code": "GRO", "number": 12 },
        { "name": "Hidalgo", "code": "HGO", "number": 13 },
        { "name": "Jalisco", "code": "JAL", "number": 14 },
        { "name": "México", "code": "MEX", "number": 15 },
        { "name": "Michoacán", "code": "MICH", "number": 16 },
        { "name": "Morelos", "code": "MOR", "number": 17 },
        { "name": "Nayarit", "code": "NAY", "number": 18 },
        { "name": "Nuevo León", "code": "NL", "number": 19 },
        { "name": "Oaxaca", "code": "OAX", "number": 20 },
        { "name": "Puebla", "code": "PUE", "number": 21 },
        { "name": "Querétaro", "code": "QRO", "number": 22 },
        { "name": "Quintana Roo", "code": "QROO", "number": 23 },
        { "name": "San Luis Potosí", "code": "SLP", "number": 24 },
        { "name": "Sinaloa", "code": "SIN", "number": 25 },
        { "name": "Sonora", "code": "SON", "number": 26 },
        { "name": "Tabasco", "code": "TAB", "number": 27 },
        { "name": "Tamaulipas", "code": "TAMPS", "number": 28 },
        { "name": "Tlaxcala", "code": "TLAX", "number": 29 },
        { "name": "Veracruz", "code": "VER", "number": 30 },
        { "name": "Yucatán", "code": "YUC", "number": 31 },
        { "name": "Zacatecas", "code": "ZAC", "number": 32 }
      ]
    }
  ]
  